mcp_songzhe_server/__init__.py
mcp_songzhe_server/server.py
mcp_songzhe_server-0.1.2.dist-info/WHEEL
mcp_songzhe_server-0.1.2.dist-info/entry_points.txt
mcp_songzhe_server-0.1.2.dist-info/METADATA
mcp_songzhe_server-0.1.2.dist-info/RECORD
